cygv/hkty.py
cygv/__init__.py
cygv/cygv.pypy310-pp73-darwin.so
cygv-0.1.1.dist-info/RECORD
cygv-0.1.1.dist-info/WHEEL
cygv-0.1.1.dist-info/METADATA
cygv-0.1.1.dist-info/license_files/LICENSE-APACHE
cygv-0.1.1.dist-info/license_files/LICENSE-MIT
